{   
    "readme": {
        "site": "obxyz.com",
        "author": "aten",
        "abbr": {
            "ar": "articles",
            "ti": "title",
            "te": "text"
        }
    },
    "ar": [
        {
            "ti": "Life is a Journey",
            "te": "Today is September 5th, 2020. I was born on June 11, 1992. My birthplace is 38°09'48.7\"N 117°12'34.9\"E. My online name is aten which I forgot why."
        },
        {
            "ti": "1599490104290",
            "te": "很多时候，我愿意作为一个观察者，看自己和这个世界。有太多的未知，不过探索的冲动很快就会被空白的大脑代替。我喜欢一个人待着，不过也很好奇别人在干些什么。生活的意义是什么，会有人天天问自己这样的问题吗？"
        },
        {
            "ti": "1599491427350",
            "te": "我经历过的事情很少，去过的地方很少，见过的人很少。读过的书很少，估计不过几十本，且大部分是在中学时期。自2011始的六七年里，看过很多的电影及美剧，约计三千小时以上。自2016年末开始玩LOL这款游戏，至今也已耗去三千小时以上。"
        },
        {
            "ti": "1599494025570",
            "te": "小学喜欢的是语文课，初中是物理课，高中是地理课。大学前预科课程，喜欢的是计算机；我开始接触互联网。大学期间主修的是英语专业，辅修的是计算机科学与技术。假定喜欢的是想象中的语言学课程，实则为欢乐的美剧时光。"
        },
        {
            "ti": "1599494821350",
            "te": "目前主要在用的两款显示器为1920*1080和2560*1440。中学时期写过两三本日记，我喜欢钢笔写字的感觉。周恩来，鲁迅，王小波，Albert Einstein，Linus Torvalds。世界这么大，我并不知道我想要去的是哪里，you are lucky if you know。"
        }
    ]
}